my_excel_automator/__init__.py
my_excel_automator/excel_automation_operations.py
my_excel_automator-1.0.0.dist-info/METADATA
my_excel_automator-1.0.0.dist-info/WHEEL
my_excel_automator-1.0.0.dist-info/entry_points.txt
my_excel_automator-1.0.0.dist-info/RECORD
