Metadata-Version: 2.1
Name: my-excel-automator
Version: 1.0.0
Summary: Generalized operations for automating excel.
Author-email: Jordan Porter <jordan@geostrategies.com>
Classifier: Operating System :: OS Independent
Classifier: Programming Language :: Python :: 3
Requires-Python: >=3.8
